gc_jira_api/Requestor.py
gc_jira_api/__init__.py
gc_jira_api/__tests__/__init__.py
gc_jira_api/__tests__/test_Requestor.py
gc_jira_api/exceptions/JiraException.py
gc_jira_api/exceptions/__init__.py
gc_jira_api/jira/__init__.py
gc_jira_api/jira/__tests__/__init__.py
gc_jira_api/jira/__tests__/test_jira_project.py
gc_jira_api-1.3.10.dist-info/LICENSE
gc_jira_api-1.3.10.dist-info/METADATA
gc_jira_api-1.3.10.dist-info/WHEEL
gc_jira_api-1.3.10.dist-info/RECORD
